{
  "project_info": {
    "project_number": "443017504333",
    "project_id": "hockeyapp-2a4d3",
    "storage_bucket": "hockeyapp-2a4d3.appspot.com"
  },
  "client": [
    {
      "client_info": {
        "mobilesdk_app_id": "1:443017504333:android:8430b6b82df7fce49f1e04",
        "android_client_info": {
          "package_name": "com.example.hockey_app"
        }
      },
      "oauth_client": [],
      "api_key": [
        {
          "current_key": "AIzaSyArZ6hVYV3Ur3mUV1tSXPr-kEr88YsJc6s"
        }
      ],
      "services": {
        "appinvite_service": {
          "other_platform_oauth_client": []
        }
      }
    }
  ],
  "configuration_version": "1"
}